setup.py
testing.py
testing2323.egg-info/PKG-INFO
testing2323.egg-info/SOURCES.txt
testing2323.egg-info/dependency_links.txt
testing2323.egg-info/top_level.txt