Metadata-Version: 1.0
Name: testing2323
Version: 0.1.0
Summary: a test
Home-page: UNKNOWN
Author: Danielle Jenkins
Author-email: djenkins@bitkitten.net
License: UNKNOWN
Platform: UNKNOWN
